s2cm/__init__.py
s2cm/client.py
s2cm/sender.py
s2cm/server.py
s2cm-0.3.2.dist-info/LICENSE
s2cm-0.3.2.dist-info/METADATA
s2cm-0.3.2.dist-info/WHEEL
s2cm-0.3.2.dist-info/top_level.txt
s2cm-0.3.2.dist-info/RECORD
